geoarrow/rust/core/__init__.py
geoarrow/rust/core/_array.pyi
geoarrow/rust/core/_array_reader.pyi
geoarrow/rust/core/_chunked_array.pyi
geoarrow/rust/core/_constructors.pyi
geoarrow/rust/core/_crs.py
geoarrow/rust/core/_data_type.pyi
geoarrow/rust/core/_interop.pyi
geoarrow/rust/core/_operations/__init__.pyi
geoarrow/rust/core/_operations/_type_id.pyi
geoarrow/rust/core/_rust.cp310-win_amd64.pyd
geoarrow/rust/core/_rust.pyi
geoarrow/rust/core/_scalar.pyi
geoarrow/rust/core/enums.py
geoarrow/rust/core/py.typed
geoarrow/rust/core/types.py
geoarrow_rust_core-0.6.0.dist-info/METADATA
geoarrow_rust_core-0.6.0.dist-info/WHEEL
geoarrow_rust_core-0.6.0.dist-info/RECORD
